basil/__init__.py
basil/_dashboard.py
basil/benchmark.py
basil/dashboard.py
basil/main.py
basil/register.py
basil/solver.py
basil/utils.py
basil_suite-0.0.1.dist-info/METADATA
basil_suite-0.0.1.dist-info/WHEEL
basil_suite-0.0.1.dist-info/entry_points.txt
basil_suite-0.0.1.dist-info/RECORD
