Metadata-Version: 2.1
Name: basil-suite
Version: 0.0.1
Summary: Benchmarking And Statistical Inspection Library
License: MIT
Keywords: benchmarking,python,simulation
Author: Antonio Stanziola
Author-email: stanziola.antonio@gmail.com
Requires-Python: >=3.10,<4.0
Classifier: License :: OSI Approved :: MIT License
Classifier: Programming Language :: Python :: 3
Classifier: Programming Language :: Python :: 3.10
Classifier: Programming Language :: Python :: 3.11
Classifier: Programming Language :: Python :: 3.8
Classifier: Programming Language :: Python :: 3.9
Classifier: Topic :: Software Development
Classifier: Topic :: Software Development :: Libraries
Requires-Dist: matplotlib (>=3.7.1,<4.0.0)
Requires-Dist: psutil (>=5.9.5,<6.0.0)
Requires-Dist: streamlit (>=1.23.1,<2.0.0)
